{
  "appointmentDetails": [
    {
      "appointmentID": "APP001",
      "appointmentDate": "07/23/2019",
      "appointmentTime": "1500"
    },
    {
      "appointmentID": "APP001",
      "appointmentDate": "07/22/2019",
      "appointmentTime": "1500"
    },
    {
      "appointmentID": "APP001",
      "appointmentDate": "07/24/2019",
      "appointmentTime": "1500"
    }
  ],
  "statusCode": "0000",
  "statusDesc": "Success",
  "authenticated": "true",
  "isSpecialUser": "true",
  "firstName": "Preetha",
  "lastName": "Prasad",
  "age": "29",
  "emailID": "preethahariprasad@gmail.com",
  "userID": "94617496",
  "planInfo": "23123123",
  "deviceID": "2131231230",
  "videoID": "plp"
}
